AI_Jarvis_Tools/Brain.py
AI_Jarvis_Tools/Clap.py
AI_Jarvis_Tools/Listen.py
AI_Jarvis_Tools/QNA.py
AI_Jarvis_Tools/Speak.py
AI_Jarvis_Tools/Wakeup.py
AI_Jarvis_Tools/__init__.py
AI_Jarvis_Tools/test.py
AI_Jarvis_Tools-0.0.3.dist-info/LICENSE
AI_Jarvis_Tools-0.0.3.dist-info/METADATA
AI_Jarvis_Tools-0.0.3.dist-info/WHEEL
AI_Jarvis_Tools-0.0.3.dist-info/top_level.txt
AI_Jarvis_Tools-0.0.3.dist-info/RECORD
