Metadata-Version: 2.1
Name: AI-Jarvis-Tools
Version: 0.0.3
Summary: AI Jarvis Tools
Author: RISHABH-SAHIL (-R-S-)
Author-email: githubsahil4@gmail.com
Keywords: AI Jarvis Tools,Rishabh Tools,Jarvis Tools,AI Jarvis,Jarvis 0.2,AI Robot Tools,Jarvis,Rishabh,Rishabh Sahil,ML Jarvis,Self learning Jarvis
Classifier: Development Status :: 1 - Planning
Classifier: Intended Audience :: Developers
Classifier: Programming Language :: Python :: 3
Classifier: Operating System :: Unix
Classifier: Operating System :: MacOS :: MacOS X
Classifier: Operating System :: Microsoft :: Windows
License-File: LICENSE
Requires-Dist: SpeechRecognition
Requires-Dist: googletrans (==3.1.0a0)
Requires-Dist: pyttsx3 (==2.90)
Requires-Dist: openai (==0.25.0)
Requires-Dist: python-dotenv (==0.21.0)
